{
	"name": "grab_success",
	"frames": [
		[
			{
				"ang": "{0.0002 89.9998 89.9997}",
				"pos": "[0 0 0]"
			},
			{
				"ang": "{62.8274 141.3001 -42.7374}",
				"pos": "[-5.512 123.7344 14.7415]"
			},
			{
				"ang": "{65.537 -4.4773 -167.9785}",
				"pos": "[0 0 0]"
			},
			{
				"ang": "{3.7338 2.5063 11.7944}",
				"pos": "[0 31.3076 -0.0002]"
			},
			{
				"ang": "{0.1593 1.328 18.288}",
				"pos": "[-0.0039 26.7822 -0.0703]"
			},
			{
				"ang": "{-27.1354 24.1795 50.8685}",
				"pos": "[0 26.5171 -0.0005]"
			},
			{
				"ang": "{53.3983 -122.9357 143.0172}",
				"pos": "[-34.4111 26.2256 2.1387]"
			},
			{
				"ang": "{-2.8041 40.9662 5.0815}",
				"pos": "[0 45.1548 0.001]"
			},
			{
				"ang": "{26.5624 8.2857 28.1432}",
				"pos": "[0 36.1316 0.001]"
			},
			{
				"ang": "{-76.798 -88.1698 -58.8808}",
				"pos": "[33.1616 24.6934 -4.4902]"
			},
			{
				"ang": "{8.552 -79.5628 7.4418}",
				"pos": "[0 45.1548 0]"
			},
			{
				"ang": "{-39.4599 5.293 -0.7704}",
				"pos": "[0 36.1318 -0.001]"
			},
			{
				"ang": "{6.8403 79.7319 39.0539}",
				"pos": "[0.0002 18.1689 13.2522]"
			},
			{
				"ang": "{1.5045 -61.9371 2.4155}",
				"pos": "[-0.001 46.4082 0.0002]"
			},
			{
				"ang": "{-80.3464 117.4613 -25.7007}",
				"pos": "[0 64.7236 0]"
			},
			{
				"ang": "{10.5519 -140.6385 -163.3482}",
				"pos": "[0 18.1699 -13.2524]"
			},
			{
				"ang": "{-1.3857 59.0826 2.3482}",
				"pos": "[0 46.4072 0]"
			},
			{
				"ang": "{67.8858 -103.2403 19.7606}",
				"pos": "[0 64.7227 0]"
			}
		],
		[
			{
				"ang": "{0.0002 89.9998 89.9997}",
				"pos": "[0 0 0]"
			},
			{
				"ang": "{62.1358 141.316 -42.8392}",
				"pos": "[-7.4867 115.0566 35.5711]"
			},
			{
				"ang": "{62.4423 -26.3611 178.4722}",
				"pos": "[0 0 0]"
			},
			{
				"ang": "{5.9896 5.2136 14.5626}",
				"pos": "[0 31.3066 0.0005]"
			},
			{
				"ang": "{-0.5397 0.2468 16.5566}",
				"pos": "[-0.0039 26.7827 -0.0703]"
			},
			{
				"ang": "{-30.7519 23.7893 45.8911}",
				"pos": "[0 26.5176 0.0005]"
			},
			{
				"ang": "{52.1966 -124.8299 157.8976}",
				"pos": "[-34.9126 24.855 1.6997]"
			},
			{
				"ang": "{-2.838 41.2875 5.106}",
				"pos": "[0 45.1548 0]"
			},
			{
				"ang": "{31.0533 -10.9272 1.3185}",
				"pos": "[0 36.1321 -0.001]"
			},
			{
				"ang": "{-84.7823 -148.5846 4.1843}",
				"pos": "[33.1611 24.6929 -4.4902]"
			},
			{
				"ang": "{2.7264 -39.8889 5.1184}",
				"pos": "[0 45.155 0]"
			},
			{
				"ang": "{-42.7665 -29.6911 -0.0218}",
				"pos": "[-0.0005 36.1313 0.001]"
			},
			{
				"ang": "{-3.013 77.3278 33.3725}",
				"pos": "[0 18.1689 13.2524]"
			},
			{
				"ang": "{2.6079 -86.1399 2.7319}",
				"pos": "[0 46.4087 -0.0002]"
			},
			{
				"ang": "{-73.4861 92.1926 20.6304}",
				"pos": "[0 64.7236 0.0001]"
			},
			{
				"ang": "{8.548 -153.7898 -158.7465}",
				"pos": "[-0.0002 18.1699 -13.252]"
			},
			{
				"ang": "{-1.2028 54.5242 2.2292}",
				"pos": "[0 46.4082 0]"
			},
			{
				"ang": "{58.6959 -110.0661 20.5004}",
				"pos": "[0 64.7227 0]"
			}
		],
		[
			{
				"ang": "{0.0002 89.9998 89.9997}",
				"pos": "[0 0 0]"
			},
			{
				"ang": "{61.1333 139.249 -44.9453}",
				"pos": "[-7.6793 109.6162 37.1008]"
			},
			{
				"ang": "{64.11 -27.6253 177.0716}",
				"pos": "[0 0 0]"
			},
			{
				"ang": "{5.6625 6.3062 16.7188}",
				"pos": "[0 31.3066 -0.0005]"
			},
			{
				"ang": "{-1.6259 -0.5178 15.6191}",
				"pos": "[-0.0039 26.7822 -0.0698]"
			},
			{
				"ang": "{-26.8293 22.073 49.5032}",
				"pos": "[0 26.5171 -0.0005]"
			},
			{
				"ang": "{55.8521 -110.7753 166.3711}",
				"pos": "[-35.2324 23.395 0.7729]"
			},
			{
				"ang": "{-4.5424 55.6797 6.014}",
				"pos": "[0.0001 45.1548 0.001]"
			},
			{
				"ang": "{27.2977 -9.7427 -5.7779}",
				"pos": "[0 36.1323 0]"
			},
			{
				"ang": "{-72.9011 -52.1495 -90.3241}",
				"pos": "[33.1616 24.6934 -4.4897]"
			},
			{
				"ang": "{6.0965 -66.85 6.5749}",
				"pos": "[0.0005 45.1548 0]"
			},
			{
				"ang": "{-44.5428 -12.3984 -2.5663}",
				"pos": "[-0.0005 36.1318 0]"
			},
			{
				"ang": "{-7.0297 82.8586 33.3226}",
				"pos": "[0 18.1699 13.2524]"
			},
			{
				"ang": "{3.0058 -94.4794 2.7293}",
				"pos": "[0 46.4087 0]"
			},
			{
				"ang": "{-72.5333 96.1386 19.4538}",
				"pos": "[0 64.7227 0.0001]"
			},
			{
				"ang": "{2.1812 -151.3123 -160.8101}",
				"pos": "[0 18.1689 -13.2524]"
			},
			{
				"ang": "{-1.5297 62.5397 2.4289}",
				"pos": "[0 46.4082 0.0005]"
			},
			{
				"ang": "{56.0718 -105.9376 30.7095}",
				"pos": "[0 64.7227 0]"
			}
		],
		[
			{
				"ang": "{0.0002 89.9998 89.9997}",
				"pos": "[0 0 0]"
			},
			{
				"ang": "{60.3043 137.4904 -46.7125}",
				"pos": "[-7.6393 108.4004 35.0135]"
			},
			{
				"ang": "{68.5401 -27.318 175.9435}",
				"pos": "[0 0 0]"
			},
			{
				"ang": "{4.355 6.7554 17.7612}",
				"pos": "[0 31.3066 0.0005]"
			},
			{
				"ang": "{-2.5549 -0.6823 15.6713}",
				"pos": "[-0.0039 26.7817 -0.0703]"
			},
			{
				"ang": "{-22.8174 18.5102 51.7893}",
				"pos": "[0 26.5171 0]"
			},
			{
				"ang": "{61.4654 -100.5689 166.574}",
				"pos": "[-35.2427 22.2261 -0.5747]"
			},
			{
				"ang": "{-8.7118 79.9231 7.5422}",
				"pos": "[0 45.1553 0]"
			},
			{
				"ang": "{21.8135 -14.9596 -2.4129}",
				"pos": "[0 36.1318 0]"
			},
			{
				"ang": "{-63.4214 -42.9169 -101.4096}",
				"pos": "[33.1611 24.6934 -4.4902]"
			},
			{
				"ang": "{7.2932 -73.7083 6.9971}",
				"pos": "[-0.0005 45.1549 0]"
			},
			{
				"ang": "{-45.5902 -9.1042 -3.8744}",
				"pos": "[0.0005 36.1321 0]"
			},
			{
				"ang": "{-8.2096 86.677 33.8251}",
				"pos": "[-0.0002 18.1699 13.2524]"
			},
			{
				"ang": "{3.0532 -95.474 2.7254}",
				"pos": "[-0.001 46.4087 0.0002]"
			},
			{
				"ang": "{-73.2288 97.8625 15.9664}",
				"pos": "[0 64.7236 -0.0002]"
			},
			{
				"ang": "{-0.209 -147.317 -162.592}",
				"pos": "[-0.0002 18.1709 -13.2524]"
			},
			{
				"ang": "{-1.7177 66.8924 2.5179}",
				"pos": "[0.0002 46.4072 0]"
			},
			{
				"ang": "{55.8137 -103.5674 34.5151}",
				"pos": "[0.0005 64.7227 0.0005]"
			}
		],
		[
			{
				"ang": "{0.0002 89.9998 89.9997}",
				"pos": "[0 0 0]"
			},
			{
				"ang": "{60.2243 137.0873 -46.8034}",
				"pos": "[-7.6534 108.3369 32.2788]"
			},
			{
				"ang": "{71.6176 -26.8979 174.6104}",
				"pos": "[0 0 0]"
			},
			{
				"ang": "{2.6861 6.9063 18.1566}",
				"pos": "[0 31.3066 0]"
			},
			{
				"ang": "{-3.1591 -0.6786 15.7949}",
				"pos": "[-0.0039 26.7822 -0.0703]"
			},
			{
				"ang": "{-20.669 16.5271 54.4248}",
				"pos": "[0.0005 26.5171 0]"
			},
			{
				"ang": "{63.939 -106.8858 156.9444}",
				"pos": "[-35.0576 21.3608 -2.1865]"
			},
			{
				"ang": "{-10.2689 86.1811 8.0068}",
				"pos": "[0.0002 45.1548 0.0005]"
			},
			{
				"ang": "{18.0475 -14.0178 -0.6384}",
				"pos": "[0.0005 36.1318 0]"
			},
			{
				"ang": "{-62.221 -42.6678 -102.9097}",
				"pos": "[33.1616 24.6934 -4.4907]"
			},
			{
				"ang": "{6.554 -69.7071 6.7255}",
				"pos": "[-0.0005 45.1553 0.001]"
			},
			{
				"ang": "{-47.2145 -14.8911 -1.3667}",
				"pos": "[0 36.1318 0]"
			},
			{
				"ang": "{-7.9066 88.8097 34.4422}",
				"pos": "[0.0005 18.1699 13.2524]"
			},
			{
				"ang": "{3.0177 -94.7222 2.7282}",
				"pos": "[-0.001 46.4084 0.0001]"
			},
			{
				"ang": "{-74.3778 99.6034 11.8707}",
				"pos": "[0 64.7227 -0.0001]"
			},
			{
				"ang": "{-1.4733 -144.1983 -163.3847}",
				"pos": "[0.0002 18.1699 -13.2522]"
			},
			{
				"ang": "{-1.8514 69.9075 2.571}",
				"pos": "[0.0002 46.4082 0.0005]"
			},
			{
				"ang": "{56.0744 -102.1093 36.0679}",
				"pos": "[0 64.7227 0]"
			}
		],
		[
			{
				"ang": "{0.0002 89.9998 89.9997}",
				"pos": "[0 0 0]"
			},
			{
				"ang": "{60.4837 136.665 -46.3045}",
				"pos": "[-7.7119 108.3525 29.1014]"
			},
			{
				"ang": "{72.5546 -23.6185 173.8275}",
				"pos": "[0 0 0]"
			},
			{
				"ang": "{1.0076 6.9123 18.3463}",
				"pos": "[0 31.3076 -0.0005]"
			},
			{
				"ang": "{-3.4833 -0.5816 16.016}",
				"pos": "[-0.0039 26.7822 -0.0703]"
			},
			{
				"ang": "{-20.4398 16.4156 58.427}",
				"pos": "[0 26.5171 0]"
			},
			{
				"ang": "{63.5681 -115.6214 147.9815}",
				"pos": "[-34.7988 20.8325 -3.9346]"
			},
			{
				"ang": "{-9.4066 82.9607 7.7368}",
				"pos": "[0 45.1548 0]"
			},
			{
				"ang": "{16.8404 -9.3342 -1.5152}",
				"pos": "[0.0005 36.1321 -0.001]"
			},
			{
				"ang": "{-64.885 -47.72 -96.7712}",
				"pos": "[33.1611 24.6938 -4.4902]"
			},
			{
				"ang": "{5.8607 -65.5444 6.4592}",
				"pos": "[0 45.155 0.001]"
			},
			{
				"ang": "{-49.2374 -20.1852 2.601}",
				"pos": "[0 36.1318 -0.001]"
			},
			{
				"ang": "{-6.6104 90.8068 34.893}",
				"pos": "[0.0005 18.1689 13.2524]"
			},
			{
				"ang": "{2.9616 -93.5449 2.7323}",
				"pos": "[0.001 46.4084 -0.0001]"
			},
			{
				"ang": "{-75.8431 102.0158 6.8517}",
				"pos": "[0.0002 64.7227 0.0001]"
			},
			{
				"ang": "{-2.9597 -140.9688 -163.5482}",
				"pos": "[0.0002 18.1699 -13.2524]"
			},
			{
				"ang": "{-1.9964 73.1027 2.6194}",
				"pos": "[0 46.4072 0]"
			},
			{
				"ang": "{56.2672 -100.6154 37.4421}",
				"pos": "[0.0005 64.7231 0]"
			}
		],
		[
			{
				"ang": "{0.0002 89.9998 89.9997}",
				"pos": "[0 0 0]"
			},
			{
				"ang": "{61.1982 136.2972 -45.7144}",
				"pos": "[-7.7659 108.3945 25.5934]"
			},
			{
				"ang": "{72.9617 -18.6303 173.861}",
				"pos": "[0 0 0]"
			},
			{
				"ang": "{-0.3419 6.9287 18.7763}",
				"pos": "[0 31.3066 -0.0002]"
			},
			{
				"ang": "{-3.6325 -0.4855 16.3381}",
				"pos": "[-0.0039 26.7822 -0.0703]"
			},
			{
				"ang": "{-20.5254 16.7551 62.9013}",
				"pos": "[0 26.5176 0]"
			},
			{
				"ang": "{62.0476 -122.1516 142.0624}",
				"pos": "[-34.5835 20.5913 -5.6621]"
			},
			{
				"ang": "{-8.0252 77.2519 7.2568}",
				"pos": "[-0.0001 45.1553 0]"
			},
			{
				"ang": "{17.4297 -4.3758 -4.0311}",
				"pos": "[0 36.1318 0]"
			},
			{
				"ang": "{-67.6241 -56.594 -85.9087}",
				"pos": "[33.1616 24.6934 -4.4902]"
			},
			{
				"ang": "{5.6381 -64.1315 6.3692}",
				"pos": "[0.001 45.1549 0]"
			},
			{
				"ang": "{-51.2191 -22.6368 6.0759}",
				"pos": "[0 36.1318 0]"
			},
			{
				"ang": "{-5.079 92.5144 35.1762}",
				"pos": "[0 18.1689 13.2524]"
			},
			{
				"ang": "{2.8895 -92.0414 2.7362}",
				"pos": "[0.001 46.4084 0]"
			},
			{
				"ang": "{-77.381 106.4753 -0.4313}",
				"pos": "[0.0002 64.7236 0]"
			},
			{
				"ang": "{-4.237 -137.9449 -163.5953}",
				"pos": "[0 18.1689 -13.2522]"
			},
			{
				"ang": "{-2.1437 76.3001 2.66}",
				"pos": "[0 46.4082 0]"
			},
			{
				"ang": "{56.4959 -99.0138 38.7774}",
				"pos": "[0.0005 64.7231 0]"
			}
		],
		[
			{
				"ang": "{0.0002 89.9998 89.9997}",
				"pos": "[0 0 0]"
			},
			{
				"ang": "{63.7354 136.1378 -45.4232}",
				"pos": "[-7.7815 108.8623 20.6719]"
			},
			{
				"ang": "{74.3818 -10.9528 176.661}",
				"pos": "[0 0 0]"
			},
			{
				"ang": "{-1.0797 7.1689 20.4228}",
				"pos": "[0 31.3066 -0.0002]"
			},
			{
				"ang": "{-3.6419 -0.4759 16.9435}",
				"pos": "[-0.0039 26.7827 -0.0708]"
			},
			{
				"ang": "{-19.3441 16.2743 67.1145}",
				"pos": "[0 26.5176 0]"
			},
			{
				"ang": "{61.9449 -122.8397 141.0555}",
				"pos": "[-34.5264 20.7261 -7.5938]"
			},
			{
				"ang": "{-7.7974 76.1923 7.1767}",
				"pos": "[0 45.1548 0.001]"
			},
			{
				"ang": "{19.0589 -2.795 -8.3192}",
				"pos": "[0 36.1318 0]"
			},
			{
				"ang": "{-68.6498 -67.719 -72.7694}",
				"pos": "[33.1616 24.6934 -4.4907]"
			},
			{
				"ang": "{6.5499 -69.6774 6.725}",
				"pos": "[0 45.155 0]"
			},
			{
				"ang": "{-52.7053 -17.5746 7.6531}",
				"pos": "[-0.0002 36.1313 0]"
			},
			{
				"ang": "{-3.4558 93.0406 34.6296}",
				"pos": "[0 18.1699 13.2524]"
			},
			{
				"ang": "{2.7492 -89.106 2.7373}",
				"pos": "[0.001 46.4087 -0.0001]"
			},
			{
				"ang": "{-78.8272 118.7559 -16.717}",
				"pos": "[0 64.7236 0]"
			},
			{
				"ang": "{-4.1854 -135.787 -163.6898}",
				"pos": "[0 18.1699 -13.2524]"
			},
			{
				"ang": "{-2.2938 79.514 2.692}",
				"pos": "[0 46.4082 0]"
			},
			{
				"ang": "{57.1095 -96.4778 40.6602}",
				"pos": "[0 64.7231 0]"
			}
		],
		[
			{
				"ang": "{0.0002 89.9998 89.9997}",
				"pos": "[0 0 0]"
			},
			{
				"ang": "{68.1685 135.1218 -46.3628}",
				"pos": "[-7.7777 110.7285 16.4199]"
			},
			{
				"ang": "{75.3623 -4.9184 -178.8685}",
				"pos": "[0 0 0]"
			},
			{
				"ang": "{-1.4277 7.5019 22.5039}",
				"pos": "[0 31.3066 0.0002]"
			},
			{
				"ang": "{-3.59 -0.5045 17.573}",
				"pos": "[-0.0039 26.7822 -0.0703]"
			},
			{
				"ang": "{-16.5831 14.6273 68.8946}",
				"pos": "[-0.0002 26.5171 0]"
			},
			{
				"ang": "{63.8394 -118.4184 143.395}",
				"pos": "[-34.4639 20.9639 -8.9346]"
			},
			{
				"ang": "{-8.9096 80.9987 7.5706}",
				"pos": "[0 45.1543 0.001]"
			},
			{
				"ang": "{17.482 -4.6769 -9.5266}",
				"pos": "[-0.0005 36.1318 0]"
			},
			{
				"ang": "{-69.9847 -74.8687 -66.2321}",
				"pos": "[33.1614 24.6934 -4.4912]"
			},
			{
				"ang": "{6.9115 -71.7007 6.8573}",
				"pos": "[-0.001 45.1549 0]"
			},
			{
				"ang": "{-50.1688 -13.689 7.9839}",
				"pos": "[0 36.1309 0]"
			},
			{
				"ang": "{-1.2906 90.3556 32.1296}",
				"pos": "[0.0002 18.1689 13.2523]"
			},
			{
				"ang": "{2.5151 -84.1948 2.7237}",
				"pos": "[0 46.4087 -0.0001]"
			},
			{
				"ang": "{-79.3618 130.6092 -32.3432}",
				"pos": "[0 64.7227 0]"
			},
			{
				"ang": "{-1.7308 -137.0356 -162.7215}",
				"pos": "[0 18.1699 -13.2524]"
			},
			{
				"ang": "{-2.2992 79.6305 2.6929}",
				"pos": "[0 46.4092 0]"
			},
			{
				"ang": "{57.9888 -93.3024 42.5369}",
				"pos": "[0.0005 64.7227 -0.0005]"
			}
		],
		[
			{
				"ang": "{0.0002 89.9998 89.9997}",
				"pos": "[0 0 0]"
			},
			{
				"ang": "{73.7177 132.6956 -48.7653}",
				"pos": "[-7.7723 113.8184 11.9496]"
			},
			{
				"ang": "{76.2897 0.431 -173.7944}",
				"pos": "[0 0 0]"
			},
			{
				"ang": "{-1.7129 7.8638 24.7741}",
				"pos": "[0 31.3066 -0.0002]"
			},
			{
				"ang": "{-3.4947 -0.543 18.3157}",
				"pos": "[-0.0039 26.7822 -0.0698]"
			},
			{
				"ang": "{-12.8181 11.9805 69.5768}",
				"pos": "[0.0002 26.5171 0]"
			},
			{
				"ang": "{67.0226 -110.1158 148.563}",
				"pos": "[-34.3411 21.2695 -10.1113]"
			},
			{
				"ang": "{-10.6914 87.588 8.1466}",
				"pos": "[0.0002 45.1553 0]"
			},
			{
				"ang": "{13.9748 -6.6789 -8.7797}",
				"pos": "[0 36.132 0]"
			},
			{
				"ang": "{-72.2 -81.6686 -61.7347}",
				"pos": "[33.1616 24.6934 -4.4897]"
			},
			{
				"ang": "{6.6546 -70.2823 6.7627}",
				"pos": "[0 45.1548 0]"
			},
			{
				"ang": "{-45.1797 -11.5729 7.8792}",
				"pos": "[0 36.1318 0]"
			},
			{
				"ang": "{1.4059 85.0591 28.3474}",
				"pos": "[-0.0001 18.1689 13.2523]"
			},
			{
				"ang": "{2.1696 -76.853 2.6658}",
				"pos": "[0 46.4087 -0.0001]"
			},
			{
				"ang": "{-79.4122 140.8008 -46.873}",
				"pos": "[-0.0001 64.7227 0]"
			},
			{
				"ang": "{2.1174 -140.023 -161.2801}",
				"pos": "[0 18.1699 -13.2523]"
			},
			{
				"ang": "{-2.2018 77.5404 2.6732}",
				"pos": "[0 46.4072 0]"
			},
			{
				"ang": "{59.0613 -88.9531 44.7298}",
				"pos": "[0 64.7231 -0.0005]"
			}
		],
		[
			{
				"ang": "{0.0002 89.9998 89.9997}",
				"pos": "[0 0 0]"
			},
			{
				"ang": "{78.7851 128.4036 -53.032}",
				"pos": "[-7.7562 117.6055 7.3611]"
			},
			{
				"ang": "{77.7878 5.2517 -169.0015}",
				"pos": "[0 0 0]"
			},
			{
				"ang": "{-1.9395 8.1666 26.7016}",
				"pos": "[0 31.3066 0]"
			},
			{
				"ang": "{-3.3647 -0.5878 19.1445}",
				"pos": "[-0.0039 26.7813 -0.0703]"
			},
			{
				"ang": "{-8.9337 8.6446 69.6163}",
				"pos": "[0 26.5171 0]"
			},
			{
				"ang": "{70.7733 -97.6462 157.6143}",
				"pos": "[-34.1719 21.624 -11.1372]"
			},
			{
				"ang": "{-12.4955 93.171 8.6704}",
				"pos": "[0 45.1553 0.001]"
			},
			{
				"ang": "{10.145 -6.903 -6.964}",
				"pos": "[0.0002 36.132 0]"
			},
			{
				"ang": "{-74.8885 -89.4735 -56.9517}",
				"pos": "[33.1616 24.6934 -4.4897]"
			},
			{
				"ang": "{5.9844 -66.3232 6.5078}",
				"pos": "[0 45.1548 0.0005]"
			},
			{
				"ang": "{-39.8495 -11.1722 7.6518}",
				"pos": "[-0 36.1318 0.0005]"
			},
			{
				"ang": "{4.0321 78.1823 24.4061}",
				"pos": "[0.0001 18.1689 13.2524]"
			},
			{
				"ang": "{1.7426 -67.465 2.5287}",
				"pos": "[0.001 46.4087 0]"
			},
			{
				"ang": "{-79.4267 146.8929 -57.8746}",
				"pos": "[0.0001 64.7236 0]"
			},
			{
				"ang": "{6.0592 -143.1964 -160.232}",
				"pos": "[0.0001 18.1689 -13.2524]"
			},
			{
				"ang": "{-2.0349 73.9334 2.6304}",
				"pos": "[0 46.4092 0]"
			},
			{
				"ang": "{60.1617 -83.537 47.1589}",
				"pos": "[0 64.7231 0]"
			}
		],
		[
			{
				"ang": "{0.0002 89.9998 89.9997}",
				"pos": "[0 0 0]"
			},
			{
				"ang": "{81.7472 124.2053 -57.1288}",
				"pos": "[-7.7292 121.6689 2.7067]"
			},
			{
				"ang": "{80.736 9.9469 -165.065}",
				"pos": "[0 0 0]"
			},
			{
				"ang": "{-2.0926 8.3168 27.7061}",
				"pos": "[0 31.3057 -0.0001]"
			},
			{
				"ang": "{-3.2014 -0.6371 20.0503}",
				"pos": "[-0.0039 26.7822 -0.0698]"
			},
			{
				"ang": "{-5.6966 4.8828 69.568}",
				"pos": "[0 26.5176 -0.001]"
			},
			{
				"ang": "{74.4465 -80.8107 171.5716}",
				"pos": "[-33.9585 22.0293 -12.0151]"
			},
			{
				"ang": "{-13.5901 96.0756 8.9738}",
				"pos": "[0.0005 45.1553 0]"
			},
			{
				"ang": "{7.332 -4.7463 -5.0583}",
				"pos": "[0 36.132 0]"
			},
			{
				"ang": "{-77.3417 -100.8943 -48.4958}",
				"pos": "[33.1611 24.6934 -4.4902]"
			},
			{
				"ang": "{5.1172 -60.5516 6.1607}",
				"pos": "[-0.0005 45.1558 0]"
			},
			{
				"ang": "{-36.235 -12.576 7.7573}",
				"pos": "[0 36.1318 0]"
			},
			{
				"ang": "{6.6387 71.2349 21.5433}",
				"pos": "[0 18.1709 13.2526]"
			},
			{
				"ang": "{1.2868 -56.6496 2.2865}",
				"pos": "[0.001 46.4087 0]"
			},
			{
				"ang": "{-80.0999 148.8378 -65.6211}",
				"pos": "[-0.0001 64.7227 0.0001]"
			},
			{
				"ang": "{8.6383 -145.1387 -160.2435}",
				"pos": "[0 18.1699 -13.2523]"
			},
			{
				"ang": "{-1.8318 69.4562 2.5632}",
				"pos": "[-0.0005 46.4092 0]"
			},
			{
				"ang": "{61.2446 -77.0565 49.8325}",
				"pos": "[0 64.7236 0]"
			}
		],
		[
			{
				"ang": "{0.0002 89.9998 89.9997}",
				"pos": "[0 0 0]"
			},
			{
				"ang": "{82.6197 123.7323 -57.3695}",
				"pos": "[-7.2151 125.5479 -1.9036]"
			},
			{
				"ang": "{84.8253 15.1257 -161.5302}",
				"pos": "[0 0 0]"
			},
			{
				"ang": "{-2.1395 8.0395 27.5229}",
				"pos": "[-0.0001 31.3066 0.0001]"
			},
			{
				"ang": "{-3.0165 -0.688 20.999}",
				"pos": "[-0.0039 26.7822 -0.0698]"
			},
			{
				"ang": "{-3.2598 1.3694 69.9945}",
				"pos": "[0 26.5176 0]"
			},
			{
				"ang": "{78.2515 -59.0445 -168.0365}",
				"pos": "[-33.7122 22.4619 -12.7676]"
			},
			{
				"ang": "{-13.4492 95.7292 8.9342}",
				"pos": "[0 45.1553 -0.001]"
			},
			{
				"ang": "{6.6424 -0.9655 -2.4196}",
				"pos": "[0 36.1318 0]"
			},
			{
				"ang": "{-78.3943 -115.7965 -36.1583}",
				"pos": "[33.1616 24.6924 -4.4897]"
			},
			{
				"ang": "{4.3536 -54.8622 5.8254}",
				"pos": "[0.0005 45.1548 0]"
			},
			{
				"ang": "{-34.7316 -14.9777 8.5868}",
				"pos": "[0 36.1318 0]"
			},
			{
				"ang": "{9.1688 66.4104 20.1132}",
				"pos": "[0 18.1709 13.2522]"
			},
			{
				"ang": "{0.9544 -47.8346 2.0289}",
				"pos": "[0 46.4082 0]"
			},
			{
				"ang": "{-81.3833 150.4192 -73.8389}",
				"pos": "[0 64.7217 -0.0001]"
			},
			{
				"ang": "{9.859 -145.4923 -161.1632}",
				"pos": "[0 18.1709 -13.2524]"
			},
			{
				"ang": "{-1.6377 65.0546 2.4821}",
				"pos": "[-0.0005 46.4092 0]"
			},
			{
				"ang": "{62.5475 -70.0772 52.8144}",
				"pos": "[-0.001 64.7227 0]"
			}
		],
		[
			{
				"ang": "{0.0002 89.9998 89.9997}",
				"pos": "[0 0 0]"
			},
			{
				"ang": "{83.0065 123.9105 -56.692}",
				"pos": "[-4.3867 129.8457 -7.344]"
			},
			{
				"ang": "{89.2812 1.2887 -177.375}",
				"pos": "[0 0 0]"
			},
			{
				"ang": "{-1.9612 6.3161 25.4622}",
				"pos": "[-0.0001 31.3066 -0.0001]"
			},
			{
				"ang": "{-2.7574 -0.7514 22.2286}",
				"pos": "[-0.0039 26.7822 -0.0703]"
			},
			{
				"ang": "{-0.6127 -1.4603 71.5675}",
				"pos": "[0 26.5176 0]"
			},
			{
				"ang": "{83.9444 15.7535 -90.5475}",
				"pos": "[-33.3682 23.0439 -13.5303]"
			},
			{
				"ang": "{-10.7352 87.7211 8.1637}",
				"pos": "[0 45.1553 0]"
			},
			{
				"ang": "{11.4382 6.6577 8.1453}",
				"pos": "[0 36.1318 -0.001]"
			},
			{
				"ang": "{-77.5562 -127.3813 -27.7133}",
				"pos": "[33.1616 24.6934 -4.4902]"
			},
			{
				"ang": "{3.8326 -50.5536 5.5871}",
				"pos": "[0.0005 45.1553 0]"
			},
			{
				"ang": "{-33.2046 -17.6041 10.6551}",
				"pos": "[-0 36.1318 0]"
			},
			{
				"ang": "{11.5735 62.1554 19.3855}",
				"pos": "[0.0001 18.1699 13.2524]"
			},
			{
				"ang": "{0.7255 -40.9962 1.7957}",
				"pos": "[0 46.4082 0]"
			},
			{
				"ang": "{-82.4284 149.0897 -79.2563}",
				"pos": "[0.0002 64.7227 0]"
			},
			{
				"ang": "{11.4078 -146.2971 -162.8615}",
				"pos": "[0.0001 18.1699 -13.2526]"
			},
			{
				"ang": "{-1.4049 59.5556 2.3599}",
				"pos": "[0 46.4082 0]"
			},
			{
				"ang": "{66.1312 -64.2007 55.017}",
				"pos": "[0 64.7236 0]"
			}
		],
		[
			{
				"ang": "{0.0002 89.9998 89.9997}",
				"pos": "[0 0 0]"
			},
			{
				"ang": "{83.1766 123.8007 -56.3376}",
				"pos": "[-1.2153 132.8623 -11.1689]"
			},
			{
				"ang": "{87.7101 -141.7431 38.2264}",
				"pos": "[0 0 0]"
			},
			{
				"ang": "{-1.7694 4.2927 22.8708}",
				"pos": "[0 31.3057 0]"
			},
			{
				"ang": "{-2.5393 -0.7997 23.2128}",
				"pos": "[-0.0039 26.7813 -0.0703]"
			},
			{
				"ang": "{1.3257 -2.6798 73.2905}",
				"pos": "[0 26.5176 0.001]"
			},
			{
				"ang": "{77.5469 80.4762 -23.0164}",
				"pos": "[-33.0728 23.5186 -14.0181]"
			},
			{
				"ang": "{-8.0016 76.964 7.273}",
				"pos": "[0.0005 45.1543 0]"
			},
			{
				"ang": "{17.9406 14.8054 18.5959}",
				"pos": "[0 36.1318 0.001]"
			},
			{
				"ang": "{-76.4232 -130.1125 -27.5861}",
				"pos": "[33.1616 24.6934 -4.4897]"
			},
			{
				"ang": "{3.6151 -48.6628 5.4841}",
				"pos": "[0 45.1548 0]"
			},
			{
				"ang": "{-31.4253 -19.0768 12.316}",
				"pos": "[-0.0001 36.1318 0]"
			},
			{
				"ang": "{13.1109 58.4227 19.0429}",
				"pos": "[0.0001 18.1689 13.2523]"
			},
			{
				"ang": "{0.6133 -37.2813 1.6578}",
				"pos": "[0 46.4087 0.0001]"
			},
			{
				"ang": "{-82.1948 141.908 -73.6366}",
				"pos": "[0.0002 64.7236 -0.0001]"
			},
			{
				"ang": "{12.3733 -147.7984 -164.54}",
				"pos": "[0.0001 18.168 -13.2524]"
			},
			{
				"ang": "{-1.2201 54.9615 2.2415}",
				"pos": "[0 46.4092 0]"
			},
			{
				"ang": "{69.8648 -61.644 55.394}",
				"pos": "[0 64.7236 -0.0002]"
			}
		],
		[
			{
				"ang": "{0.0002 89.9998 89.9997}",
				"pos": "[0 0 0]"
			},
			{
				"ang": "{83.2663 123.6373 -56.0484}",
				"pos": "[2.0802 135.5156 -14.2953]"
			},
			{
				"ang": "{85.4222 -141.0276 37.8056}",
				"pos": "[0 0 0]"
			},
			{
				"ang": "{-1.6303 2.0537 19.7302}",
				"pos": "[0 31.3076 -0.0001]"
			},
			{
				"ang": "{-2.3166 -0.8443 24.1803}",
				"pos": "[-0.0039 26.7813 -0.0698]"
			},
			{
				"ang": "{3.0035 -3.1676 75.2451}",
				"pos": "[0.0001 26.5171 0.001]"
			},
			{
				"ang": "{70.2287 101.6142 -1.7803}",
				"pos": "[-32.7715 23.9912 -14.4106]"
			},
			{
				"ang": "{-5.5445 63.33 6.3549}",
				"pos": "[0 45.1548 0]"
			},
			{
				"ang": "{24.2088 23.8275 25.4892}",
				"pos": "[-0.0001 36.1318 0]"
			},
			{
				"ang": "{-75.3752 -129.0671 -31.2789}",
				"pos": "[33.1614 24.6934 -4.4902]"
			},
			{
				"ang": "{3.4643 -47.3045 5.4112}",
				"pos": "[0 45.1538 0]"
			},
			{
				"ang": "{-28.9412 -20.0649 13.4187}",
				"pos": "[0.0001 36.1309 0]"
			},
			{
				"ang": "{14.1716 54.6361 18.8488}",
				"pos": "[-0.0001 18.1699 13.2522]"
			},
			{
				"ang": "{0.5655 -35.5956 1.5928}",
				"pos": "[0.0005 46.4087 -0.0001]"
			},
			{
				"ang": "{-81.0117 132.0752 -62.198}",
				"pos": "[0 64.7227 0]"
			},
			{
				"ang": "{13.1806 -149.712 -166.3184}",
				"pos": "[-0.0001 18.1689 -13.2526]"
			},
			{
				"ang": "{-1.0446 50.3446 2.1076}",
				"pos": "[0.0005 46.4082 0]"
			},
			{
				"ang": "{73.2318 -58.9834 56.0869}",
				"pos": "[0 64.7236 0.0002]"
			}
		],
		[
			{
				"ang": "{0.0002 89.9998 89.9997}",
				"pos": "[0 0 0]"
			},
			{
				"ang": "{83.3293 123.6194 -55.705}",
				"pos": "[4.8239 137.8096 -16.5258]"
			},
			{
				"ang": "{83.8197 -138.7371 39.1817}",
				"pos": "[0 0 0]"
			},
			{
				"ang": "{-1.5869 -0.0153 16.3901}",
				"pos": "[0.0001 31.3066 0]"
			},
			{
				"ang": "{-2.0964 -0.8841 25.108}",
				"pos": "[-0.0039 26.7822 -0.0703]"
			},
			{
				"ang": "{4.2651 -3.1739 77.2231}",
				"pos": "[0 26.5171 -0.0005]"
			},
			{
				"ang": "{65.1964 116.7913 11.2445}",
				"pos": "[-32.4688 24.457 -14.718]"
			},
			{
				"ang": "{-3.5645 48.1545 5.4706}",
				"pos": "[-0.0005 45.1548 -0.0005]"
			},
			{
				"ang": "{29.7719 31.8376 28.2734}",
				"pos": "[0.0002 36.1318 0]"
			},
			{
				"ang": "{-74.5189 -126.2241 -36.6575}",
				"pos": "[33.1616 24.6934 -4.49]"
			},
			{
				"ang": "{3.2834 -45.6302 5.3227}",
				"pos": "[0.0005 45.1553 0]"
			},
			{
				"ang": "{-25.863 -20.8096 13.6242}",
				"pos": "[0.0001 36.1309 0]"
			},
			{
				"ang": "{14.8274 51.2486 18.7124}",
				"pos": "[-0.0001 18.1699 13.2523]"
			},
			{
				"ang": "{0.5631 -35.491 1.5889}",
				"pos": "[0 46.4082 0.0002]"
			},
			{
				"ang": "{-79.4704 124.8107 -52.1509}",
				"pos": "[0.0001 64.7236 -0.0001]"
			},
			{
				"ang": "{14.0512 -151.7385 -167.9705}",
				"pos": "[-0.0001 18.1699 -13.2523]"
			},
			{
				"ang": "{-0.8836 45.8052 1.9625}",
				"pos": "[0 46.4072 0]"
			},
			{
				"ang": "{75.2109 -53.5848 59.4365}",
				"pos": "[0 64.7227 0.0002]"
			}
		],
		[
			{
				"ang": "{0.0002 89.9998 89.9997}",
				"pos": "[0 0 0]"
			},
			{
				"ang": "{83.4105 123.9806 -55.1649}",
				"pos": "[6.2347 139.7207 -17.5497]"
			},
			{
				"ang": "{83.0938 -137.2877 39.9628}",
				"pos": "[0 0 0]"
			},
			{
				"ang": "{-1.6076 -1.4967 13.1641}",
				"pos": "[0.0002 31.3076 0]"
			},
			{
				"ang": "{-1.8861 -0.9182 25.9723}",
				"pos": "[-0.0039 26.7822 -0.0703]"
			},
			{
				"ang": "{4.8672 -2.9148 79.0255}",
				"pos": "[0 26.5176 0]"
			},
			{
				"ang": "{61.7639 130.2885 21.7595}",
				"pos": "[-32.1785 24.9014 -14.9463]"
			},
			{
				"ang": "{-2.0879 33.2436 4.7421}",
				"pos": "[0.0005 45.1543 0]"
			},
			{
				"ang": "{34.691 36.8889 27.7595}",
				"pos": "[0.0001 36.1318 0]"
			},
			{
				"ang": "{-73.7769 -123.4491 -41.5338}",
				"pos": "[33.1614 24.6934 -4.4905]"
			},
			{
				"ang": "{2.9782 -42.6992 5.1731}",
				"pos": "[0 45.1543 0]"
			},
			{
				"ang": "{-22.4843 -21.6277 12.7637}",
				"pos": "[0 36.1309 0]"
			},
			{
				"ang": "{15.3347 47.978 18.3208}",
				"pos": "[-0.0002 18.1709 13.2524]"
			},
			{
				"ang": "{0.5587 -35.3335 1.5828}",
				"pos": "[0 46.4092 0.0001]"
			},
			{
				"ang": "{-78.2702 120.8544 -45.4955}",
				"pos": "[0 64.7217 0]"
			},
			{
				"ang": "{14.8838 -154.229 -169.1846}",
				"pos": "[-0.0001 18.1699 -13.2522]"
			},
			{
				"ang": "{-0.7282 41.0804 1.7983}",
				"pos": "[-0.0005 46.4092 0]"
			},
			{
				"ang": "{75.8217 -47.8488 63.0581}",
				"pos": "[0 64.7227 0]"
			}
		],
		[
			{
				"ang": "{0.0002 89.9998 89.9997}",
				"pos": "[0 0 0]"
			},
			{
				"ang": "{83.2981 127.7412 -51.3936}",
				"pos": "[6.2423 141.3027 -17.3727]"
			},
			{
				"ang": "{83.0426 -138.3075 38.4808}",
				"pos": "[0 0 0]"
			},
			{
				"ang": "{-1.6115 -2.3436 10.3244}",
				"pos": "[0.0002 31.3066 -0.0001]"
			},
			{
				"ang": "{-1.6899 -0.9469 26.7632}",
				"pos": "[-0.0039 26.7832 -0.0704]"
			},
			{
				"ang": "{4.6619 -2.3544 80.5058}",
				"pos": "[0 26.5176 0]"
			},
			{
				"ang": "{59.7434 139.3653 27.8605}",
				"pos": "[-31.8997 25.3154 -15.1156]"
			},
			{
				"ang": "{-1.1422 21.7613 4.2694}",
				"pos": "[0 45.1553 0]"
			},
			{
				"ang": "{38.4801 38.3165 25.7041}",
				"pos": "[0.0001 36.1318 0]"
			},
			{
				"ang": "{-72.5462 -123.6342 -42.6817}",
				"pos": "[33.1615 24.6934 -4.49]"
			},
			{
				"ang": "{2.5858 -38.7212 4.9725}",
				"pos": "[0 45.1553 -0.0002]"
			},
			{
				"ang": "{-19.5024 -22.0493 11.3971}",
				"pos": "[-0.0002 36.1318 0]"
			},
			{
				"ang": "{16.1135 44.99 17.9273}",
				"pos": "[-0.0001 18.1689 13.2524]"
			},
			{
				"ang": "{0.5266 -34.1615 1.5366}",
				"pos": "[0 46.4082 -0.0002]"
			},
			{
				"ang": "{-77.8763 118.9557 -42.0209}",
				"pos": "[0.0001 64.7227 0]"
			},
			{
				"ang": "{15.2762 -157.4075 -169.9102}",
				"pos": "[-0.0001 18.1689 -13.2523]"
			},
			{
				"ang": "{-0.5788 36.0576 1.6106}",
				"pos": "[0 46.4072 0]"
			},
			{
				"ang": "{76.1368 -45.8578 62.998}",
				"pos": "[0.0002 64.7236 0]"
			}
		],
		[
			{
				"ang": "{0.0002 89.9998 89.9997}",
				"pos": "[0 0 0]"
			},
			{
				"ang": "{81.7687 142.567 -36.6535}",
				"pos": "[5.0558 142.7754 -15.5143]"
			},
			{
				"ang": "{83.26 -146.11 30.3774}",
				"pos": "[0 0 0]"
			},
			{
				"ang": "{-1.4773 -2.9608 7.5639}",
				"pos": "[-0.0001 31.3057 0]"
			},
			{
				"ang": "{-1.4789 -0.9745 27.5954}",
				"pos": "[-0.0039 26.7822 -0.0704]"
			},
			{
				"ang": "{2.8602 -0.6115 81.8106}",
				"pos": "[0.0001 26.5176 0.0005]"
			},
			{
				"ang": "{61.4452 138.1479 22.9371}",
				"pos": "[-31.5924 25.7666 -15.2446]"
			},
			{
				"ang": "{-0.8373 17.6878 4.151}",
				"pos": "[0 45.1553 -0.0005]"
			},
			{
				"ang": "{40.8724 35.6467 23.6537}",
				"pos": "[0.0001 36.1318 0]"
			},
			{
				"ang": "{-68.1472 -130.5033 -36.0293}",
				"pos": "[33.1616 24.6934 -4.4904]"
			},
			{
				"ang": "{2.2131 -34.703 4.7834}",
				"pos": "[-0.0005 45.1543 0]"
			},
			{
				"ang": "{-17.8987 -19.6011 10.4115}",
				"pos": "[0 36.1309 0.0002]"
			},
			{
				"ang": "{19.1974 38.2781 17.7848}",
				"pos": "[-0.0001 18.1689 13.2524]"
			},
			{
				"ang": "{0.3385 -26.3499 1.2147}",
				"pos": "[0 46.4092 0.0001]"
			},
			{
				"ang": "{-78.1647 122.4792 -43.7882}",
				"pos": "[0.0001 64.7217 0]"
			},
			{
				"ang": "{14.3113 -162.1339 -170.5419}",
				"pos": "[0 18.1699 -13.2523]"
			},
			{
				"ang": "{-0.4097 29.5249 1.3487}",
				"pos": "[0.0002 46.4082 0]"
			},
			{
				"ang": "{76.5597 -48.095 58.3306}",
				"pos": "[-0.0002 64.7227 0]"
			}
		],
		[
			{
				"ang": "{0.0002 89.9998 89.9997}",
				"pos": "[0 0 0]"
			},
			{
				"ang": "{79.583 152.9495 -26.3592}",
				"pos": "[3.7148 143.6201 -13.4132]"
			},
			{
				"ang": "{83.3465 -155.3767 21.0499}",
				"pos": "[0 0 0]"
			},
			{
				"ang": "{-1.3044 -3.2591 5.9094}",
				"pos": "[0 31.3066 -0.0001]"
			},
			{
				"ang": "{-1.3437 -0.9903 28.1206}",
				"pos": "[-0.0039 26.7822 -0.0703]"
			},
			{
				"ang": "{0.7238 1.0912 82.4981}",
				"pos": "[0 26.5176 0]"
			},
			{
				"ang": "{64.3244 127.7522 10.1637}",
				"pos": "[-31.3854 26.0713 -15.3009]"
			},
			{
				"ang": "{-1.1013 21.2193 4.2534}",
				"pos": "[0 45.1548 -0.0005]"
			},
			{
				"ang": "{41.6632 31.1541 22.7212}",
				"pos": "[0 36.1318 0]"
			},
			{
				"ang": "{-62.9402 -136.2556 -29.8092}",
				"pos": "[33.1615 24.6934 -4.4903]"
			},
			{
				"ang": "{2.0098 -32.4105 4.6799}",
				"pos": "[0 45.1553 0]"
			},
			{
				"ang": "{-18.1812 -16.1641 9.9969}",
				"pos": "[0 36.1318 0]"
			},
			{
				"ang": "{23.2503 28.8093 16.3503}",
				"pos": "[-0.0001 18.1689 13.2522]"
			},
			{
				"ang": "{0.1332 -13.7728 0.6512}",
				"pos": "[0 46.4082 0.0001]"
			},
			{
				"ang": "{-78.639 126.5009 -47.2781}",
				"pos": "[0 64.7227 -0.0001]"
			},
			{
				"ang": "{13.0864 -166.088 -170.7131}",
				"pos": "[0 18.1689 -13.2526]"
			},
			{
				"ang": "{-0.2934 24.1205 1.1181}",
				"pos": "[0 46.4102 -0.0002]"
			},
			{
				"ang": "{76.9231 -52.1906 52.2667}",
				"pos": "[0 64.7236 -0.0002]"
			}
		],
		[
			{
				"ang": "{0.0002 89.9998 89.9997}",
				"pos": "[0 0 0]"
			},
			{
				"ang": "{77.0642 159.7315 -19.6795}",
				"pos": "[2.3193 144.2021 -11.2255]"
			},
			{
				"ang": "{83.2556 -165.0264 11.4768}",
				"pos": "[0 0 0]"
			},
			{
				"ang": "{-1.1116 -3.425 4.724}",
				"pos": "[0 31.3066 -0.0001]"
			},
			{
				"ang": "{-1.245 -1.0013 28.4982}",
				"pos": "[-0.0039 26.7832 -0.0703]"
			},
			{
				"ang": "{-1.5605 2.7426 82.9201}",
				"pos": "[0.0002 26.5166 0]"
			},
			{
				"ang": "{66.0386 112.8855 -6.7079}",
				"pos": "[-31.2211 26.3105 -15.3293]"
			},
			{
				"ang": "{-1.482 26.0883 4.421}",
				"pos": "[0 45.1548 0]"
			},
			{
				"ang": "{41.6691 26.9674 22.1334}",
				"pos": "[0 36.1313 -0.001]"
			},
			{
				"ang": "{-57.3282 -140.3141 -25.01}",
				"pos": "[33.1615 24.6934 -4.4901]"
			},
			{
				"ang": "{1.8769 -30.8714 4.6135}",
				"pos": "[0 45.1553 -0.0002]"
			},
			{
				"ang": "{-19.3256 -12.2511 9.4771}",
				"pos": "[0 36.1318 0]"
			},
			{
				"ang": "{27.3353 19.3351 13.8673}",
				"pos": "[0.0001 18.1689 13.2523]"
			},
			{
				"ang": "{0.0557 -1.4952 0.0714}",
				"pos": "[0.0002 46.4092 -0.0001]"
			},
			{
				"ang": "{-79.2395 127.6123 -49.2822}",
				"pos": "[0.0002 64.7227 0]"
			},
			{
				"ang": "{11.9185 -170.015 -170.6079}",
				"pos": "[0.0001 18.1699 -13.2526]"
			},
			{
				"ang": "{-0.1962 18.5414 0.8699}",
				"pos": "[0 46.4082 0]"
			},
			{
				"ang": "{77.1856 -57.1431 45.2365}",
				"pos": "[-0.0001 64.7227 0]"
			}
		],
		[
			{
				"ang": "{0.0002 89.9998 89.9997}",
				"pos": "[0 0 0]"
			},
			{
				"ang": "{74.8775 163.5743 -15.9166}",
				"pos": "[1.157 144.5566 -9.4056]"
			},
			{
				"ang": "{83.0465 -172.6495 3.9876}",
				"pos": "[0 0 0]"
			},
			{
				"ang": "{-0.9445 -3.5003 3.9708}",
				"pos": "[-0.0002 31.3057 -0.0001]"
			},
			{
				"ang": "{-1.1885 -1.0068 28.7129}",
				"pos": "[-0.0038 26.7822 -0.0703]"
			},
			{
				"ang": "{-3.4846 4.0548 83.1582}",
				"pos": "[-0.0001 26.5176 0]"
			},
			{
				"ang": "{66.0644 99.7178 -21.4339}",
				"pos": "[-31.105 26.4746 -15.3383]"
			},
			{
				"ang": "{-1.7889 29.8271 4.5677}",
				"pos": "[0 45.1543 0.0005]"
			},
			{
				"ang": "{41.2637 24.1711 21.7682}",
				"pos": "[0 36.1318 0.001]"
			},
			{
				"ang": "{-52.6518 -142.614 -21.9572}",
				"pos": "[33.1614 24.6943 -4.4903]"
			},
			{
				"ang": "{1.802 -29.9795 4.5756}",
				"pos": "[0 45.1543 0]"
			},
			{
				"ang": "{-20.5773 -8.8139 8.7935}",
				"pos": "[-0.0001 36.1328 0]"
			},
			{
				"ang": "{29.6995 17.414 13.6055}",
				"pos": "[0 18.1689 13.2523]"
			},
			{
				"ang": "{0.0551 -0.7143 0.0375}",
				"pos": "[0.0002 46.4092 -0.0001]"
			},
			{
				"ang": "{-79.537 128.6987 -49.0115}",
				"pos": "[-0.0002 64.7227 0.0001]"
			},
			{
				"ang": "{11.0806 -173.6239 -170.4078}",
				"pos": "[0 18.1689 -13.2526]"
			},
			{
				"ang": "{-0.1257 13.1519 0.6223}",
				"pos": "[0 46.4082 0]"
			},
			{
				"ang": "{77.2676 -61.1572 39.1571}",
				"pos": "[0 64.7227 0]"
			}
		]
	]
}